uceasy/__init__.py
uceasy/adapters.py
uceasy/console.py
uceasy/facade.py
uceasy/ioutils.py
uceasy/operations.py
uceasy/run.py
uceasy/tracking.py
uceasy-0.3.1.dist-info/LICENSE
uceasy-0.3.1.dist-info/METADATA
uceasy-0.3.1.dist-info/WHEEL
uceasy-0.3.1.dist-info/entry_points.txt
uceasy-0.3.1.dist-info/RECORD
