Metadata-Version: 2.1
Name: uceasy
Version: 0.3.1
Summary: Wrapper for the Phyluce phylogenomics software package
Home-page: https://uceasy.github.io
License: MIT
Keywords: uce,phyluce,ultraconserved elements
Author: Caio Raposo
Author-email: caioraposo@protonmail.com
Requires-Python: >=3.7,<4.0
Classifier: License :: OSI Approved :: MIT License
Classifier: Programming Language :: Python :: 3
Classifier: Programming Language :: Python :: 3.7
Classifier: Programming Language :: Python :: 3.8
Classifier: Programming Language :: Python :: 3.9
Classifier: Programming Language :: Python :: 3.10
Classifier: Programming Language :: Python :: 3.11
Requires-Dist: click (>=8.0,<9.0)
Project-URL: Repository, https://github.com/uceasy/uceasy
